{"v":"2.1","w":204,"h":244,"fps":5,"bg":"ffffff","f":[[{"d":0,"s":0,"e":136,"c":"000000","n":2,"r":1,"w":0,"v":0,"x":-236,"y":-189},{"d":1,"s":0,"e":133,"c":"000000","n":2,"r":1,"w":0,"v":0,"x":-236,"y":-189}],[{"d":2,"s":0,"e":85,"c":"000000","n":2,"r":1,"w":0,"v":0,"x":-236,"y":-189},{"d":3,"s":0,"e":238,"c":"000000","n":2,"r":1,"w":0,"v":0,"x":-236,"y":-189}],[{"d":4,"s":0,"e":61,"c":"000000","n":2,"r":1,"w":0,"v":0,"x":-236,"y":-189},{"d":5,"s":0,"e":187,"c":"000000","n":2,"r":1,"w":0,"v":0,"x":-236,"y":-189}],[{"d":6,"s":0,"e":207,"c":"000000","n":2,"r":1,"w":0,"v":0,"x":-236,"y":-189}],[{"d":7,"s":0,"e":58,"c":"000000","n":2,"r":1,"w":0,"v":0,"x":-236,"y":-189}],[{"d":8,"s":0,"e":83,"c":"000000","n":2,"r":1,"w":0,"v":0,"x":-236,"y":-189}],[{"d":9,"s":0,"e":148,"c":"000000","n":2,"r":1,"w":0,"v":0,"x":-236,"y":-189}],[{"d":10,"s":0,"e":128,"c":"000000","n":2,"r":1,"w":0,"v":0,"x":-236,"y":-189}]],"d":[[{"x":384,"y":278},{"x":384,"y":276},{"x":384,"y":276},{"x":383,"y":279},{"x":374,"y":288},{"x":365,"y":296},{"x":353,"y":307},{"x":346,"y":313},{"x":338,"y":324},{"x":331,"y":331},{"x":325,"y":335},{"x":324,"y":336},{"x":324,"y":336},{"x":324,"y":336},{"x":324,"y":335},{"x":324,"y":329},{"x":327,"y":321},{"x":334,"y":309},{"x":337,"y":302},{"x":342,"y":290},{"x":346,"y":282},{"x":349,"y":275},{"x":350,"y":271},{"x":353,"y":266},{"x":356,"y":262},"end",{"x":382,"y":281},{"x":386,"y":280},{"x":388,"y":280},{"x":388,"y":281},{"x":393,"y":285},{"x":399,"y":289},{"x":409,"y":295},{"x":412,"y":298},{"x":418,"y":301},{"x":423,"y":305},{"x":428,"y":311},{"x":431,"y":313},{"x":432,"y":314},{"x":434,"y":315},{"x":435,"y":315},{"x":435,"y":316},{"x":436,"y":316},{"x":436,"y":316},{"x":436,"y":316},{"x":436,"y":315},{"x":435,"y":307},{"x":433,"y":301},{"x":432,"y":294},{"x":430,"y":290},{"x":428,"y":285},{"x":424,"y":279},{"x":420,"y":277},{"x":418,"y":276},{"x":412,"y":272},{"x":410,"y":270},{"x":409,"y":267},{"x":408,"y":265},{"x":407,"y":264},{"x":404,"y":264},{"x":399,"y":263},{"x":398,"y":262},{"x":398,"y":262},{"x":398,"y":261},{"x":397,"y":261},{"x":397,"y":261},{"x":397,"y":260},{"x":392,"y":259},"end",{"x":354,"y":257},{"x":355,"y":255},{"x":365,"y":246},{"x":372,"y":233},{"x":380,"y":222},{"x":389,"y":210},{"x":397,"y":205},{"x":409,"y":200},{"x":420,"y":195},{"x":422,"y":194},{"x":422,"y":193},{"x":422,"y":193},{"x":422,"y":193},{"x":421,"y":193},{"x":416,"y":202},{"x":409,"y":213},{"x":402,"y":224},{"x":400,"y":229},{"x":396,"y":236},{"x":394,"y":242},{"x":393,"y":247},{"x":393,"y":248},{"x":393,"y":248},{"x":393,"y":248},"end",{"x":370,"y":255},{"x":370,"y":253},{"x":370,"y":253},{"x":370,"y":253},{"x":370,"y":254},{"x":370,"y":254},{"x":370,"y":254},{"x":370,"y":254},{"x":370,"y":254},{"x":370,"y":254},{"x":370,"y":254},{"x":370,"y":254},{"x":370,"y":254},{"x":370,"y":255},"end",{"x":381,"y":254},"end",{"x":382,"y":254},{"x":383,"y":253},{"x":385,"y":252},{"x":385,"y":252},{"x":384,"y":252},{"x":383,"y":253},{"x":383,"y":253},{"x":384,"y":253},{"x":384,"y":253},"end",{"x":378,"y":267},{"x":377,"y":265},{"x":377,"y":265},{"x":377,"y":265},{"x":377,"y":265},{"x":377,"y":265},{"x":377,"y":265},{"x":378,"y":265},{"x":378,"y":265},{"x":378,"y":265},{"x":378,"y":265},{"x":378,"y":265},{"x":378,"y":265},"end",{"x":369,"y":292}],[{"x":398,"y":284},{"x":396,"y":284},{"x":395,"y":287},{"x":391,"y":293},{"x":389,"y":298},{"x":388,"y":301},{"x":386,"y":304},{"x":386,"y":305},{"x":386,"y":305},{"x":386,"y":305},"end",{"x":385,"y":284},{"x":385,"y":282},{"x":385,"y":282},{"x":385,"y":282},{"x":385,"y":282},{"x":385,"y":282},{"x":385,"y":282},{"x":385,"y":282},{"x":385,"y":296},{"x":385,"y":300},{"x":385,"y":302},{"x":385,"y":302},{"x":385,"y":302},{"x":385,"y":302},{"x":384,"y":302},"end",{"x":374,"y":294},{"x":375,"y":292},{"x":375,"y":292},{"x":375,"y":292},{"x":375,"y":292},{"x":377,"y":295},{"x":381,"y":302},{"x":381,"y":305},{"x":382,"y":306},{"x":383,"y":309},{"x":384,"y":310},{"x":385,"y":311},{"x":386,"y":312},{"x":386,"y":319},{"x":385,"y":324},{"x":385,"y":326},{"x":385,"y":332},{"x":385,"y":337},{"x":384,"y":341},{"x":384,"y":345},{"x":384,"y":352},{"x":384,"y":356},{"x":384,"y":360},{"x":384,"y":362},{"x":383,"y":365},{"x":382,"y":370},{"x":381,"y":373},{"x":381,"y":376},{"x":380,"y":381},{"x":378,"y":383},{"x":378,"y":384},{"x":378,"y":388},{"x":376,"y":391},{"x":375,"y":396},{"x":374,"y":398},{"x":374,"y":400},{"x":373,"y":405},{"x":372,"y":408},{"x":372,"y":408},{"x":371,"y":410},{"x":371,"y":410},{"x":371,"y":410},{"x":371,"y":410},"end",{"x":372,"y":409},{"x":373,"y":408},{"x":381,"y":406},{"x":382,"y":405},{"x":382,"y":408},{"x":382,"y":413},{"x":377,"y":414},{"x":376,"y":414},{"x":372,"y":413},{"x":369,"y":412},{"x":369,"y":412},{"x":370,"y":411},{"x":371,"y":410},{"x":371,"y":410},{"x":371,"y":410},{"x":371,"y":410},{"x":371,"y":410},{"x":371,"y":410},{"x":370,"y":411},{"x":369,"y":413},{"x":368,"y":415},{"x":366,"y":416},{"x":365,"y":417},{"x":364,"y":417},{"x":363,"y":414},{"x":363,"y":409},{"x":363,"y":407},{"x":368,"y":407},{"x":369,"y":407},{"x":370,"y":407},{"x":370,"y":408},{"x":371,"y":410},{"x":371,"y":410},{"x":371,"y":410},{"x":371,"y":410},{"x":371,"y":409},{"x":371,"y":406},{"x":372,"y":404},{"x":376,"y":404},{"x":377,"y":404},{"x":378,"y":404},{"x":378,"y":406},{"x":378,"y":408},{"x":378,"y":410},{"x":375,"y":411},{"x":372,"y":411},{"x":372,"y":411},{"x":372,"y":411},{"x":372,"y":411},{"x":373,"y":411},{"x":377,"y":415},{"x":378,"y":416},{"x":378,"y":420},{"x":377,"y":421},{"x":374,"y":421},{"x":372,"y":421},{"x":371,"y":420},{"x":370,"y":412},{"x":370,"y":412},{"x":370,"y":412},{"x":376,"y":411},"end"],[{"x":371,"y":417},{"x":369,"y":418},{"x":364,"y":416},{"x":364,"y":410},{"x":364,"y":408},{"x":365,"y":403},{"x":370,"y":403},{"x":371,"y":403},{"x":374,"y":404},{"x":374,"y":408},{"x":374,"y":410},{"x":373,"y":410},{"x":373,"y":410},{"x":373,"y":406},{"x":374,"y":403},{"x":379,"y":403},{"x":381,"y":404},{"x":382,"y":408},{"x":382,"y":410},{"x":379,"y":413},{"x":376,"y":412},{"x":374,"y":411},{"x":374,"y":410},{"x":374,"y":410},{"x":382,"y":410},{"x":387,"y":409},{"x":387,"y":409},{"x":387,"y":414},{"x":386,"y":416},{"x":382,"y":418},{"x":382,"y":418},{"x":380,"y":418},{"x":378,"y":413},{"x":378,"y":413},{"x":378,"y":413},{"x":378,"y":413},{"x":379,"y":415},{"x":380,"y":418},{"x":379,"y":421},{"x":375,"y":422},{"x":372,"y":423},{"x":371,"y":423},{"x":371,"y":423},{"x":371,"y":421},{"x":370,"y":417},{"x":371,"y":414},{"x":373,"y":414},{"x":376,"y":413},"end",{"x":374,"y":411},{"x":373,"y":408},{"x":374,"y":401},{"x":375,"y":396},{"x":376,"y":390},{"x":379,"y":385},{"x":383,"y":381},{"x":387,"y":375},{"x":388,"y":374},{"x":388,"y":374},{"x":388,"y":374},{"x":388,"y":374},"end",{"x":385,"y":364},{"x":383,"y":364},{"x":383,"y":364},{"x":383,"y":364},{"x":383,"y":363},"end",{"x":396,"y":361},{"x":395,"y":359},{"x":395,"y":359},{"x":395,"y":359},{"x":395,"y":359},"end",{"x":400,"y":379},"end",{"x":397,"y":374},{"x":398,"y":374},{"x":398,"y":373},{"x":398,"y":373},"end",{"x":394,"y":385},{"x":395,"y":385},{"x":395,"y":385},"end"],[{"x":396,"y":342},{"x":397,"y":337},{"x":397,"y":336},{"x":397,"y":333},{"x":397,"y":330},{"x":397,"y":326},{"x":395,"y":322},{"x":394,"y":316},{"x":393,"y":312},{"x":391,"y":307},{"x":390,"y":302},{"x":388,"y":298},{"x":386,"y":293},{"x":384,"y":289},{"x":380,"y":286},{"x":377,"y":283},{"x":373,"y":282},{"x":370,"y":281},{"x":364,"y":279},{"x":361,"y":277},{"x":359,"y":276},{"x":358,"y":275},{"x":358,"y":275},{"x":357,"y":275},{"x":357,"y":275},{"x":357,"y":275},{"x":357,"y":275},{"x":357,"y":275},{"x":357,"y":275},{"x":357,"y":275},{"x":357,"y":274},{"x":356,"y":272},{"x":353,"y":269},{"x":350,"y":267},{"x":350,"y":267},{"x":349,"y":267},{"x":349,"y":267},{"x":349,"y":267},{"x":349,"y":267},{"x":350,"y":270},{"x":353,"y":273},{"x":355,"y":275},{"x":355,"y":275},{"x":355,"y":276},{"x":355,"y":276},{"x":355,"y":276},{"x":355,"y":276},{"x":355,"y":276},{"x":355,"y":276},{"x":350,"y":274},{"x":348,"y":272},{"x":344,"y":272},{"x":344,"y":272},{"x":344,"y":272},{"x":344,"y":272},{"x":344,"y":272},{"x":348,"y":273},{"x":353,"y":276},{"x":357,"y":276},{"x":357,"y":277},{"x":357,"y":277},{"x":357,"y":277},{"x":357,"y":277},{"x":354,"y":278},{"x":348,"y":279},{"x":346,"y":281},{"x":346,"y":281},{"x":346,"y":281},{"x":346,"y":281},"end",{"x":344,"y":275},{"x":343,"y":276},{"x":344,"y":278},{"x":345,"y":284},{"x":345,"y":293},{"x":345,"y":303},{"x":344,"y":312},{"x":339,"y":323},{"x":336,"y":331},{"x":332,"y":336},{"x":327,"y":342},{"x":324,"y":342},{"x":323,"y":343},{"x":322,"y":343},{"x":321,"y":344},{"x":321,"y":344},{"x":321,"y":344},{"x":321,"y":344},{"x":321,"y":344},{"x":321,"y":344},{"x":321,"y":344},{"x":321,"y":344},{"x":321,"y":344},{"x":321,"y":341},{"x":320,"y":337},{"x":320,"y":331},{"x":320,"y":326},{"x":321,"y":322},{"x":321,"y":316},{"x":321,"y":310},{"x":321,"y":309},{"x":321,"y":305},{"x":321,"y":299},{"x":321,"y":297},{"x":321,"y":295},{"x":321,"y":291},{"x":321,"y":288},{"x":321,"y":285},{"x":320,"y":283},{"x":320,"y":283},{"x":320,"y":283},{"x":320,"y":283},{"x":320,"y":283},{"x":320,"y":283},{"x":319,"y":283},{"x":318,"y":285},{"x":315,"y":289},{"x":313,"y":292},{"x":312,"y":297},{"x":308,"y":308},{"x":306,"y":315},{"x":304,"y":321},{"x":301,"y":327},{"x":296,"y":332},{"x":291,"y":339},{"x":290,"y":343},{"x":290,"y":343},{"x":290,"y":344},{"x":290,"y":344},{"x":290,"y":344},{"x":289,"y":338},{"x":289,"y":332},{"x":289,"y":323},{"x":289,"y":315},{"x":293,"y":306},{"x":297,"y":296},{"x":301,"y":287},{"x":305,"y":283},{"x":312,"y":277},{"x":317,"y":272},{"x":318,"y":271},{"x":318,"y":270},{"x":318,"y":270},{"x":318,"y":270},{"x":318,"y":270},{"x":318,"y":270},{"x":318,"y":270},{"x":318,"y":270},"end",{"x":320,"y":269},{"x":318,"y":267},{"x":318,"y":266},{"x":323,"y":263},{"x":332,"y":257},{"x":337,"y":253},{"x":339,"y":252},{"x":339,"y":252},{"x":339,"y":251},{"x":340,"y":250},{"x":347,"y":246},{"x":359,"y":239},{"x":374,"y":231},{"x":384,"y":229},{"x":395,"y":228},{"x":409,"y":228},{"x":420,"y":230},{"x":428,"y":231},{"x":432,"y":232},{"x":432,"y":232},{"x":432,"y":232},{"x":431,"y":232},{"x":427,"y":233},{"x":425,"y":233},{"x":422,"y":236},{"x":415,"y":239},{"x":407,"y":241},{"x":393,"y":246},{"x":384,"y":250},{"x":377,"y":252},{"x":369,"y":254},{"x":366,"y":257},{"x":365,"y":260},{"x":365,"y":261},{"x":365,"y":261},{"x":365,"y":261},{"x":365,"y":261},"end",{"x":352,"y":267},{"x":351,"y":265},{"x":352,"y":265},{"x":352,"y":265},{"x":360,"y":259},{"x":368,"y":256},{"x":372,"y":254},{"x":374,"y":254},"end",{"x":333,"y":261},"end",{"x":338,"y":262},{"x":336,"y":261},{"x":336,"y":261},{"x":336,"y":261},{"x":336,"y":261},{"x":336,"y":261},{"x":336,"y":261},{"x":336,"y":261},{"x":336,"y":261},{"x":336,"y":262},{"x":336,"y":262},"end",{"x":342,"y":261},"end",{"x":346,"y":266},{"x":344,"y":264},{"x":344,"y":264},{"x":344,"y":264},{"x":344,"y":264},{"x":344,"y":264},{"x":344,"y":264},{"x":344,"y":263},{"x":344,"y":263},{"x":344,"y":263},{"x":344,"y":263},{"x":344,"y":263},{"x":344,"y":263},{"x":344,"y":263},{"x":344,"y":263},{"x":344,"y":263},"end",{"x":332,"y":270},{"x":331,"y":271},{"x":331,"y":272},{"x":331,"y":272},{"x":332,"y":271},{"x":332,"y":271},{"x":332,"y":271},{"x":332,"y":271},"end"],[{"x":373,"y":416},{"x":372,"y":416},{"x":367,"y":417},{"x":366,"y":419},{"x":365,"y":419},{"x":364,"y":410},{"x":364,"y":407},{"x":366,"y":404},{"x":372,"y":404},{"x":373,"y":410},{"x":373,"y":411},{"x":373,"y":411},{"x":373,"y":412},{"x":373,"y":412},{"x":374,"y":409},{"x":374,"y":405},{"x":380,"y":403},{"x":381,"y":403},{"x":382,"y":409},{"x":382,"y":411},{"x":381,"y":412},{"x":377,"y":412},{"x":376,"y":411},{"x":376,"y":411},{"x":377,"y":411},{"x":384,"y":411},{"x":384,"y":413},{"x":384,"y":416},{"x":384,"y":417},{"x":382,"y":419},{"x":376,"y":418},{"x":376,"y":417},{"x":376,"y":414},{"x":378,"y":414},{"x":380,"y":417},{"x":380,"y":422},{"x":379,"y":425},{"x":373,"y":424},{"x":371,"y":423},{"x":370,"y":419},{"x":370,"y":416},{"x":370,"y":413},"end",{"x":374,"y":413},{"x":375,"y":413},{"x":374,"y":414},{"x":374,"y":414},{"x":373,"y":407},{"x":372,"y":402},{"x":372,"y":399},{"x":372,"y":394},{"x":377,"y":388},{"x":378,"y":386},{"x":378,"y":383},{"x":380,"y":380},{"x":382,"y":376},{"x":382,"y":375},{"x":382,"y":374},{"x":382,"y":373},{"x":382,"y":373},"end"],[{"x":387,"y":240},{"x":387,"y":236},{"x":385,"y":234},{"x":381,"y":233},{"x":376,"y":230},{"x":365,"y":229},{"x":356,"y":228},{"x":348,"y":228},{"x":340,"y":231},{"x":334,"y":239},{"x":328,"y":243},{"x":323,"y":248},{"x":320,"y":253},{"x":319,"y":258},{"x":318,"y":261},{"x":318,"y":261},{"x":318,"y":261},{"x":318,"y":261},{"x":318,"y":260},"end",{"x":321,"y":252},{"x":319,"y":252},{"x":317,"y":254},{"x":315,"y":256},{"x":312,"y":260},{"x":308,"y":261},{"x":308,"y":261},"end",{"x":323,"y":252},{"x":321,"y":250},{"x":321,"y":250},{"x":321,"y":250},{"x":321,"y":250},{"x":321,"y":254},{"x":321,"y":259},{"x":321,"y":266},{"x":322,"y":269},{"x":322,"y":270},{"x":322,"y":270},{"x":322,"y":270},"end",{"x":317,"y":263},{"x":318,"y":262},{"x":323,"y":268},{"x":328,"y":272},{"x":332,"y":278},{"x":334,"y":284},{"x":336,"y":294},{"x":337,"y":299},{"x":339,"y":307},{"x":339,"y":319},{"x":339,"y":333},{"x":339,"y":344},{"x":337,"y":354},{"x":333,"y":366},{"x":327,"y":375},{"x":323,"y":380},{"x":323,"y":380},{"x":323,"y":380},{"x":323,"y":380},{"x":324,"y":379},{"x":325,"y":377},{"x":325,"y":370},{"x":326,"y":360},{"x":326,"y":355},{"x":326,"y":350},{"x":323,"y":343},{"x":320,"y":335},{"x":318,"y":332},{"x":317,"y":327},{"x":315,"y":322},{"x":313,"y":317},{"x":311,"y":314},{"x":311,"y":308},{"x":310,"y":305},{"x":309,"y":304},{"x":308,"y":302},{"x":307,"y":301},{"x":307,"y":301},{"x":306,"y":301},{"x":306,"y":301},{"x":306,"y":301},{"x":306,"y":301},{"x":306,"y":301},{"x":306,"y":303},{"x":303,"y":307},{"x":301,"y":313},{"x":297,"y":320},{"x":296,"y":330},{"x":295,"y":340},{"x":294,"y":351},{"x":293,"y":361},{"x":292,"y":369},{"x":292,"y":374},{"x":292,"y":377},{"x":291,"y":382},{"x":291,"y":382},{"x":291,"y":382},{"x":290,"y":382},{"x":290,"y":382},{"x":290,"y":381},{"x":287,"y":375},{"x":287,"y":369},{"x":286,"y":361},{"x":285,"y":349},{"x":284,"y":339},{"x":284,"y":324},{"x":286,"y":311},{"x":290,"y":299},{"x":291,"y":295},{"x":293,"y":291},{"x":296,"y":287},{"x":296,"y":287},{"x":296,"y":287},{"x":295,"y":287},{"x":292,"y":289},{"x":289,"y":288},{"x":287,"y":289},{"x":282,"y":290},{"x":274,"y":297},{"x":269,"y":300},{"x":264,"y":307},{"x":256,"y":312},{"x":252,"y":318},{"x":247,"y":329},{"x":243,"y":332},{"x":243,"y":332},{"x":243,"y":332},{"x":241,"y":335},{"x":241,"y":335},{"x":241,"y":335},{"x":241,"y":335},{"x":241,"y":328},{"x":241,"y":323},{"x":240,"y":314},{"x":241,"y":306},{"x":246,"y":300},{"x":251,"y":292},{"x":257,"y":285},{"x":262,"y":279},{"x":269,"y":272},{"x":280,"y":267},{"x":281,"y":266},{"x":287,"y":265},{"x":294,"y":264},{"x":301,"y":263},{"x":302,"y":263},{"x":307,"y":263},{"x":310,"y":263},{"x":313,"y":263},{"x":314,"y":263},{"x":314,"y":263},{"x":315,"y":263},"end",{"x":306,"y":275},{"x":305,"y":276},{"x":305,"y":276},{"x":305,"y":275},{"x":305,"y":275},"end",{"x":314,"y":278},"end",{"x":316,"y":275},{"x":316,"y":276},{"x":316,"y":276},{"x":317,"y":275},{"x":317,"y":274},{"x":317,"y":274},{"x":317,"y":274},{"x":317,"y":275},{"x":317,"y":276},{"x":317,"y":276},"end",{"x":312,"y":284},{"x":312,"y":285},{"x":312,"y":285},{"x":312,"y":285},{"x":312,"y":286},{"x":312,"y":286},{"x":312,"y":286},{"x":312,"y":286},{"x":312,"y":286},{"x":312,"y":285},{"x":312,"y":284},{"x":312,"y":284},{"x":312,"y":284},"end"],[{"x":372,"y":415},{"x":372,"y":413},{"x":372,"y":413},{"x":372,"y":418},{"x":368,"y":419},{"x":365,"y":419},{"x":364,"y":418},{"x":364,"y":406},{"x":364,"y":404},{"x":365,"y":402},{"x":370,"y":403},{"x":374,"y":407},{"x":375,"y":407},{"x":375,"y":410},{"x":375,"y":410},{"x":375,"y":410},{"x":375,"y":409},{"x":374,"y":402},{"x":374,"y":399},{"x":381,"y":399},{"x":384,"y":400},{"x":384,"y":404},{"x":384,"y":407},{"x":383,"y":409},{"x":377,"y":408},{"x":377,"y":408},{"x":377,"y":408},{"x":378,"y":408},{"x":388,"y":408},{"x":388,"y":408},{"x":388,"y":412},{"x":387,"y":414},{"x":382,"y":415},{"x":380,"y":416},{"x":378,"y":414},{"x":376,"y":411},{"x":375,"y":411},{"x":375,"y":411},{"x":375,"y":411},{"x":375,"y":412},{"x":376,"y":412},"end",{"x":378,"y":409},{"x":378,"y":404},{"x":377,"y":399},{"x":374,"y":395},{"x":374,"y":390},{"x":380,"y":385},{"x":381,"y":385},{"x":381,"y":385},{"x":383,"y":385},{"x":385,"y":382},"end",{"x":356,"y":221},{"x":355,"y":218},{"x":354,"y":217},{"x":350,"y":217},{"x":342,"y":216},{"x":337,"y":216},{"x":332,"y":217},{"x":327,"y":231},{"x":323,"y":241},{"x":319,"y":253},{"x":318,"y":261},{"x":316,"y":275},{"x":311,"y":289},{"x":308,"y":302},{"x":308,"y":309},{"x":308,"y":314},{"x":308,"y":314},{"x":308,"y":314},{"x":308,"y":314},{"x":308,"y":314},{"x":308,"y":310},"end",{"x":316,"y":312},{"x":315,"y":313},{"x":314,"y":312},{"x":314,"y":314},{"x":322,"y":324},{"x":328,"y":331},{"x":331,"y":341},{"x":333,"y":355},{"x":333,"y":364},{"x":329,"y":381},{"x":322,"y":394},{"x":319,"y":403},{"x":314,"y":411},{"x":309,"y":414},{"x":309,"y":414},{"x":309,"y":414},{"x":309,"y":414},{"x":309,"y":413},{"x":310,"y":408},{"x":310,"y":404},{"x":310,"y":397},{"x":310,"y":390},{"x":310,"y":380},{"x":310,"y":368},{"x":309,"y":364},{"x":307,"y":358},{"x":305,"y":350},{"x":304,"y":345},{"x":304,"y":345},{"x":304,"y":344},{"x":304,"y":344},{"x":304,"y":344},{"x":303,"y":345},{"x":300,"y":357},{"x":299,"y":367},{"x":299,"y":381},{"x":297,"y":393},{"x":292,"y":405},{"x":286,"y":411},{"x":282,"y":421},{"x":276,"y":426},{"x":275,"y":429},{"x":275,"y":429},{"x":275,"y":429},{"x":275,"y":429},{"x":275,"y":429},{"x":275,"y":429},{"x":275,"y":428},{"x":275,"y":424},{"x":276,"y":421},{"x":276,"y":419},{"x":276,"y":413},{"x":277,"y":405},{"x":281,"y":394},{"x":282,"y":384},{"x":284,"y":368},{"x":289,"y":358},{"x":289,"y":353},{"x":289,"y":350},{"x":289,"y":345},{"x":289,"y":345},{"x":289,"y":345},{"x":289,"y":344},{"x":289,"y":344},{"x":289,"y":344},{"x":289,"y":344},{"x":288,"y":344},{"x":287,"y":345},{"x":277,"y":354},{"x":274,"y":359},{"x":270,"y":369},{"x":264,"y":381},{"x":260,"y":399},{"x":258,"y":411},{"x":256,"y":420},{"x":255,"y":423},{"x":255,"y":423},{"x":255,"y":423},{"x":255,"y":422},{"x":255,"y":414},{"x":255,"y":410},{"x":255,"y":399},{"x":258,"y":387},{"x":264,"y":376},{"x":270,"y":365},{"x":277,"y":349},{"x":286,"y":333},{"x":291,"y":328},{"x":299,"y":317},{"x":305,"y":311},{"x":306,"y":311},{"x":306,"y":311},{"x":307,"y":308},"end",{"x":307,"y":330},{"x":304,"y":328},{"x":304,"y":328},{"x":304,"y":328},{"x":304,"y":328},{"x":304,"y":328},{"x":304,"y":328},{"x":302,"y":329},{"x":302,"y":329},{"x":302,"y":329},{"x":303,"y":329},{"x":303,"y":329},{"x":303,"y":329},{"x":304,"y":329},"end",{"x":313,"y":329},{"x":313,"y":330},{"x":313,"y":330},{"x":313,"y":330},{"x":313,"y":330},{"x":313,"y":330},{"x":313,"y":330},{"x":313,"y":330},{"x":314,"y":328},{"x":315,"y":328},"end",{"x":308,"y":339},{"x":309,"y":337},{"x":309,"y":337},{"x":309,"y":337},{"x":309,"y":337},{"x":308,"y":337},{"x":308,"y":337},{"x":308,"y":337},{"x":307,"y":339},{"x":306,"y":340},{"x":307,"y":339},"end"],[{"x":367,"y":415},{"x":365,"y":414},{"x":362,"y":404},{"x":362,"y":399},{"x":363,"y":398},{"x":370,"y":398},{"x":374,"y":403},{"x":374,"y":408},{"x":373,"y":412},{"x":372,"y":412},{"x":372,"y":412},{"x":372,"y":412},{"x":372,"y":409},{"x":376,"y":401},{"x":380,"y":398},{"x":382,"y":398},{"x":383,"y":400},{"x":383,"y":407},{"x":383,"y":408},{"x":382,"y":409},{"x":376,"y":409},{"x":376,"y":409},{"x":377,"y":409},{"x":382,"y":409},{"x":385,"y":409},{"x":386,"y":411},{"x":387,"y":415},{"x":387,"y":418},{"x":385,"y":419},{"x":381,"y":419},{"x":376,"y":414},{"x":376,"y":413},{"x":376,"y":412},{"x":376,"y":412},{"x":376,"y":412},{"x":379,"y":415},{"x":379,"y":419},{"x":379,"y":421},{"x":374,"y":424},{"x":370,"y":423},{"x":368,"y":422},{"x":368,"y":417},{"x":368,"y":415},"end",{"x":374,"y":408},{"x":373,"y":409},{"x":373,"y":410},{"x":373,"y":410},{"x":373,"y":408},{"x":373,"y":400},{"x":373,"y":394},{"x":375,"y":390},{"x":378,"y":386},{"x":380,"y":386},{"x":381,"y":385},{"x":382,"y":384},{"x":382,"y":383},"end"],[{"x":372,"y":417},{"x":371,"y":417},{"x":365,"y":416},{"x":361,"y":415},{"x":360,"y":407},{"x":360,"y":402},{"x":362,"y":399},{"x":367,"y":399},{"x":369,"y":399},{"x":371,"y":404},{"x":371,"y":408},{"x":371,"y":409},{"x":371,"y":409},{"x":371,"y":409},{"x":371,"y":409},{"x":372,"y":407},{"x":378,"y":400},{"x":380,"y":398},{"x":382,"y":397},{"x":384,"y":397},{"x":385,"y":400},{"x":385,"y":405},{"x":384,"y":407},{"x":380,"y":408},{"x":376,"y":408},{"x":375,"y":407},{"x":375,"y":407},{"x":381,"y":407},{"x":384,"y":407},{"x":386,"y":408},{"x":386,"y":410},{"x":386,"y":414},{"x":383,"y":414},{"x":382,"y":414},{"x":379,"y":414},{"x":378,"y":412},{"x":378,"y":412},{"x":379,"y":412},{"x":383,"y":412},{"x":383,"y":418},{"x":381,"y":420},{"x":378,"y":421},{"x":374,"y":420},{"x":371,"y":418},{"x":370,"y":415},{"x":370,"y":412},"end",{"x":377,"y":406},{"x":375,"y":406},{"x":375,"y":406},{"x":375,"y":406},{"x":374,"y":401},{"x":372,"y":398},{"x":373,"y":392},{"x":375,"y":387},{"x":377,"y":383},{"x":380,"y":377},{"x":383,"y":373},{"x":387,"y":368},{"x":389,"y":366},{"x":390,"y":364},{"x":390,"y":361},{"x":391,"y":358},{"x":391,"y":357},{"x":391,"y":357},{"x":391,"y":357},"end",{"x":391,"y":354},{"x":388,"y":351},{"x":388,"y":348},{"x":387,"y":344},{"x":387,"y":344},{"x":390,"y":344},{"x":394,"y":344},{"x":394,"y":344},{"x":393,"y":347},{"x":393,"y":348},{"x":392,"y":352},{"x":391,"y":353},{"x":391,"y":354},{"x":391,"y":355},{"x":389,"y":355},"end"],[{"x":367,"y":417},{"x":367,"y":415},{"x":366,"y":414},{"x":362,"y":411},{"x":362,"y":405},{"x":362,"y":403},{"x":362,"y":401},{"x":370,"y":400},{"x":371,"y":401},{"x":371,"y":407},{"x":371,"y":407},{"x":371,"y":407},{"x":371,"y":409},{"x":371,"y":409},{"x":374,"y":402},{"x":379,"y":397},{"x":381,"y":396},{"x":382,"y":397},{"x":382,"y":402},{"x":382,"y":406},{"x":380,"y":406},{"x":378,"y":405},{"x":378,"y":404},{"x":379,"y":404},{"x":385,"y":404},{"x":386,"y":408},{"x":386,"y":410},{"x":386,"y":412},{"x":381,"y":413},{"x":380,"y":413},{"x":380,"y":413},{"x":380,"y":413},{"x":380,"y":413},{"x":380,"y":413},{"x":379,"y":413},{"x":374,"y":413},{"x":371,"y":412},"end",{"x":374,"y":407},{"x":373,"y":405},{"x":373,"y":405},{"x":373,"y":403},{"x":374,"y":395},{"x":374,"y":387},{"x":375,"y":379},{"x":378,"y":370},{"x":381,"y":364},{"x":385,"y":362},{"x":387,"y":359},{"x":389,"y":356},{"x":389,"y":354},{"x":389,"y":351},{"x":389,"y":346},{"x":389,"y":342},{"x":389,"y":341},{"x":389,"y":340},{"x":387,"y":338},{"x":387,"y":338},{"x":387,"y":338},{"x":387,"y":341},"end",{"x":389,"y":341},{"x":387,"y":341},{"x":387,"y":341},{"x":387,"y":341},{"x":387,"y":341},{"x":387,"y":341},{"x":383,"y":337},{"x":380,"y":334},{"x":379,"y":331},{"x":379,"y":329},{"x":378,"y":326},{"x":377,"y":322},{"x":377,"y":320},{"x":377,"y":319},{"x":377,"y":317},{"x":377,"y":317},{"x":379,"y":315},{"x":381,"y":314},{"x":382,"y":314},{"x":382,"y":314},{"x":382,"y":314},{"x":382,"y":314},{"x":383,"y":315},{"x":384,"y":321},{"x":384,"y":324},{"x":385,"y":327},{"x":385,"y":330},{"x":386,"y":332},{"x":386,"y":334},{"x":386,"y":336},{"x":386,"y":338},{"x":386,"y":338},{"x":386,"y":338},{"x":386,"y":338},{"x":388,"y":338},{"x":391,"y":334},{"x":391,"y":333},{"x":392,"y":330},{"x":392,"y":326},{"x":392,"y":323},{"x":392,"y":321},{"x":391,"y":318},{"x":391,"y":316},{"x":389,"y":316},{"x":389,"y":315},{"x":388,"y":314},{"x":386,"y":313},{"x":384,"y":313},{"x":384,"y":313},{"x":384,"y":313},{"x":384,"y":313},{"x":383,"y":316},{"x":382,"y":323},{"x":382,"y":328},{"x":383,"y":331},{"x":384,"y":332},{"x":385,"y":335},{"x":386,"y":336},{"x":386,"y":337},{"x":386,"y":338},{"x":386,"y":338},{"x":386,"y":338},{"x":386,"y":338},{"x":387,"y":338},{"x":389,"y":338},{"x":390,"y":338},{"x":392,"y":336},{"x":394,"y":332},{"x":394,"y":329},{"x":394,"y":324},{"x":395,"y":322},{"x":395,"y":319},{"x":395,"y":316},{"x":393,"y":314},{"x":392,"y":314},{"x":391,"y":314},{"x":389,"y":314},{"x":386,"y":317},{"x":385,"y":323},{"x":385,"y":327},{"x":385,"y":334},{"x":386,"y":337},{"x":387,"y":339},{"x":387,"y":341},{"x":387,"y":341},{"x":387,"y":341},"end"],[{"x":375,"y":408},{"x":375,"y":406},{"x":374,"y":405},{"x":374,"y":399},{"x":381,"y":394},{"x":381,"y":394},{"x":381,"y":394},{"x":384,"y":400},{"x":383,"y":404},{"x":379,"y":404},{"x":376,"y":405},{"x":371,"y":405},{"x":371,"y":405},{"x":379,"y":405},{"x":384,"y":404},{"x":386,"y":405},{"x":386,"y":409},{"x":385,"y":412},{"x":381,"y":415},{"x":378,"y":414},{"x":377,"y":412},{"x":377,"y":409},{"x":377,"y":409},{"x":378,"y":409},{"x":382,"y":410},{"x":381,"y":414},{"x":374,"y":415},{"x":369,"y":413},{"x":367,"y":409},{"x":366,"y":405},{"x":365,"y":404},{"x":365,"y":404},{"x":371,"y":402},"end",{"x":378,"y":406},{"x":376,"y":404},{"x":376,"y":404},{"x":376,"y":400},{"x":375,"y":395},{"x":375,"y":388},{"x":379,"y":382},{"x":380,"y":373},{"x":386,"y":362},{"x":390,"y":357},{"x":393,"y":349},{"x":395,"y":345},{"x":396,"y":341},{"x":396,"y":337},{"x":396,"y":333},{"x":395,"y":329},{"x":390,"y":324},{"x":389,"y":319},{"x":388,"y":317},{"x":386,"y":314},{"x":385,"y":311},{"x":384,"y":311},{"x":384,"y":310},{"x":384,"y":310},"end",{"x":382,"y":309},{"x":382,"y":307},{"x":382,"y":307},{"x":382,"y":307},{"x":377,"y":308},{"x":374,"y":306},{"x":371,"y":300},{"x":369,"y":297},{"x":368,"y":294},{"x":366,"y":290},{"x":365,"y":287},{"x":365,"y":287},{"x":365,"y":286},{"x":365,"y":285},{"x":364,"y":285},{"x":364,"y":285},{"x":364,"y":285},{"x":364,"y":285},{"x":364,"y":285},{"x":364,"y":285},{"x":364,"y":284},{"x":365,"y":284},{"x":371,"y":289},{"x":372,"y":290},{"x":372,"y":293},{"x":373,"y":293},{"x":373,"y":293},{"x":373,"y":293},{"x":373,"y":293},{"x":373,"y":290},{"x":373,"y":283},{"x":373,"y":279},{"x":373,"y":278},{"x":374,"y":276},{"x":374,"y":275},{"x":375,"y":275},{"x":375,"y":275},{"x":375,"y":275},{"x":375,"y":275},{"x":375,"y":277},{"x":375,"y":281},{"x":376,"y":284},{"x":377,"y":285},{"x":377,"y":286},{"x":378,"y":288},{"x":378,"y":288},{"x":378,"y":288},{"x":378,"y":288},{"x":379,"y":286},{"x":380,"y":278},{"x":383,"y":275},{"x":383,"y":274},{"x":384,"y":273},{"x":386,"y":273},{"x":386,"y":273},{"x":386,"y":274},{"x":386,"y":279},{"x":386,"y":281},{"x":386,"y":287},{"x":386,"y":292},{"x":386,"y":294},{"x":386,"y":297},{"x":386,"y":302},{"x":386,"y":304},{"x":386,"y":307},{"x":385,"y":310},{"x":382,"y":311},{"x":382,"y":311},"end"]]}